<?xml version="1.0" encoding="UTF-8"?>
<objects serializationModel="Studio.02.00.00">
	<object class="AudioFile" id="{0f454c63-5044-4975-8e29-bf928d3b0042}">
		<property name="assetPath">
			<value>Sounds/Kie/Walking/Walking_Gravel/Walking_Gravel 3-Footsteps, Gravel, Sneaker, Medium SND1052.wav</value>
		</property>
		<property name="frequencyInKHz">
			<value>48</value>
		</property>
		<property name="channelCount">
			<value>2</value>
		</property>
		<property name="length">
			<value>0.35193750000000001</value>
		</property>
		<relationship name="masterAssetFolder">
			<destination>{7fed7cee-e3f3-4e92-a997-b7d772d33a6e}</destination>
		</relationship>
	</object>
</objects>
